fetchx/__init__.py
fetchx/_call.py
fetchx/common.py
fetchx/fetchx.py
fetchx/generaltypes.py
fetchx/ioutils.py
fetchx/init/__init__.py
fetchx/init/init.py
fetchx/init/init_files.py
fetchx-0.0.44.dist-info/METADATA
fetchx-0.0.44.dist-info/WHEEL
fetchx-0.0.44.dist-info/top_level.txt
fetchx-0.0.44.dist-info/RECORD
