Metadata-Version: 2.1
Name: fetchx
Version: 0.0.44
Summary: fetchx library and its two main functions "call" and "fetch" are designed to allow users to rapidly scrape/automate web applications.
Home-page: UNKNOWN
Author: Jaromir Sivic
Author-email: unknown@unknown.com
License: MIT
Keywords: fetch,fetchx,httpx,http 2
Platform: UNKNOWN
Classifier: License :: OSI Approved :: MIT License
Classifier: Programming Language :: Python :: 3.10
Classifier: Operating System :: OS Independent
Requires-Python: >=3.10
Requires-Dist: httpx
Requires-Dist: h2
Provides-Extra: dev
Requires-Dist: twine (>=4.0.2) ; extra == 'dev'
